seo_bhishma_cli/__init__.py
seo_bhishma_cli/cli.py
seo_bhishma_cli/constants.py
seo_bhishma_cli/domain_insight.py
seo_bhishma_cli/gsc_probe.py
seo_bhishma_cli/hannibal.py
seo_bhishma_cli/index_spy.py
seo_bhishma_cli/keyword_sorcerer.py
seo_bhishma_cli/link_sniper.py
seo_bhishma_cli/redirection_genius.py
seo_bhishma_cli/site_mapper.py
seo_bhishma_cli/sitemap_generator.py
seo_bhishma_cli/common/__init__.py
seo_bhishma_cli-2.0.0.dist-info/LICENSE
seo_bhishma_cli-2.0.0.dist-info/METADATA
seo_bhishma_cli-2.0.0.dist-info/WHEEL
seo_bhishma_cli-2.0.0.dist-info/entry_points.txt
seo_bhishma_cli-2.0.0.dist-info/top_level.txt
seo_bhishma_cli-2.0.0.dist-info/RECORD
