Metadata-Version: 2.1
Name: seo-bhishma-cli
Version: 2.0.0
Summary: A CLI tool for SEO tasks including sitemap downloading, indexing checks, backlink live checks, and more.
Home-page: https://github.com/anonymousraft/seo-bhishma-cli
Author: Hitendra Rathore
Author-email: hitendra1995@mail.com
License: MIT
Project-URL: Documentation, https://github.com/anonymousraft/seo-bhishma-cli#readme
Project-URL: Source, https://github.com/anonymousraft/seo-bhishma-cli
Project-URL: Tracker, https://github.com/anonymousraft/seo-bhishma-cli/issues
Keywords: SEO,CLI,sitemap,indexing,backlinks
Classifier: Development Status :: 5 - Production/Stable
Classifier: Intended Audience :: Developers
Classifier: Intended Audience :: Information Technology
Classifier: Topic :: Software Development :: Build Tools
Classifier: Programming Language :: Python :: 3
Classifier: Programming Language :: Python :: 3.6
Classifier: Programming Language :: Python :: 3.7
Classifier: Programming Language :: Python :: 3.8
Classifier: Programming Language :: Python :: 3.9
Classifier: License :: OSI Approved :: MIT License
Classifier: Operating System :: OS Independent
Requires-Python: >=3.6
License-File: LICENSE
Requires-Dist: click
Requires-Dist: requests
Requires-Dist: beautifulsoup4
Requires-Dist: pandas
Requires-Dist: art
Requires-Dist: lxml
Requires-Dist: scikit-learn
Requires-Dist: openai
Requires-Dist: pyyaml
Requires-Dist: rich
Requires-Dist: google-auth
Requires-Dist: google-auth-oauthlib
Requires-Dist: google-api-python-client
Requires-Dist: numpy
Requires-Dist: spacy
Requires-Dist: dnspython
Requires-Dist: ipwhois
Requires-Dist: sublist3r
Requires-Dist: python-whois
Requires-Dist: geopy
Requires-Dist: fake-useragent
Requires-Dist: python-wappalyzer
Requires-Dist: requests-html
Requires-Dist: lxml-html-clean
Requires-Dist: browserforge
Requires-Dist: playwright
